{
  "version": "1.6.3",
  "description": "Securely manage your secrets and environment variables with Phase.",
  "homepage": "https://github.com/phasehq/cli",
  "license": "GPLv3",
  "url": "https://github.com/phasehq/cli/releases/download/v1.6.3/phase_cli_windows_amd64_1.6.3.exe",
  "hash": "sha256:225793fa611e1eca02e55a438f40daf27a193cd94cd207f434a69a129df3a90d",
  "installer": {
    "script": [
      "Rename-Item \"$dir\\phase_cli_windows_amd64_1.6.3.exe\" 'phase.exe'"
    ]
  },
  "bin": "phase.exe",
  "shortcuts": [["phase.exe", "Phase"]],
  "checkver": {
    "github": "https://github.com/phasehq/cli",
    "regex": "tag/v([\\w.-]+)"
  },
  "autoupdate": {
    "url": "https://github.com/phasehq/cli/releases/download/v$version/phase_cli_windows_amd64_$version.exe"
  }
}
